qpdk/__init__.py
qpdk/config.py
qpdk/helper.py
qpdk/layers.yaml
qpdk/tech.py
qpdk/cells/__init__.py
qpdk/cells/airbridge.py
qpdk/cells/bump.py
qpdk/cells/capacitor.py
qpdk/cells/chip.py
qpdk/cells/helpers.py
qpdk/cells/junction.py
qpdk/cells/launcher.py
qpdk/cells/resonator.py
qpdk/cells/snspd.py
qpdk/cells/transmon.py
qpdk/cells/tsv.py
qpdk/cells/waveguides.py
qpdk/cells/derived/__init__.py
qpdk/cells/derived/transmon_with_resonator.py
qpdk/klayout/layers.lyp
qpdk/klayout/tech.lyt
qpdk/models/README.md
qpdk/models/__init__.py
qpdk/models/couplers.py
qpdk/models/generic.py
qpdk/models/media.py
qpdk/models/resonator.py
qpdk/models/waveguides.py
qpdk/samples/all_cells.py
qpdk/samples/filled_resonator.py
qpdk/samples/filled_test_chip.py
qpdk/samples/flipmon_test_chip.pic.yml
qpdk/samples/flipmon_test_chip.scm.yml
qpdk/samples/qubit_test_chip.pic.yml
qpdk/samples/qubit_test_chip.scm.yml
qpdk/samples/resonator_test_chip.py
qpdk/samples/resonator_test_chip_yaml.pic.yml
qpdk/samples/resonator_test_chip_yaml.scm.yml
qpdk/samples/route_sample_all_angle.py
qpdk/samples/route_with_airbridges.py
qpdk/samples/sample0.py
qpdk/samples/sample1.py
qpdk/samples/sample2.py
qpdk/samples/sample3.py
qpdk/samples/sample4.py
qpdk/samples/sample5.py
qpdk/samples/sample6.py
qpdk/samples/simulate_resonator.py
qpdk-0.1.3.dist-info/licenses/LICENSE
qpdk-0.1.3.dist-info/WHEEL
qpdk-0.1.3.dist-info/METADATA
qpdk-0.1.3.dist-info/RECORD
