Metadata-Version: 2.4
Name: qpdk
Version: 0.1.3
Summary: Quantum-RF generic PDK
Keywords: python
Author-email: gdsfactory <contact@gdsfactory.com>
Requires-Python: >=3.12,<3.14
Classifier: Operating System :: OS Independent
Classifier: Programming Language :: Python :: 3.12
Classifier: Programming Language :: Python :: 3.13
Classifier: Programming Language :: Python :: 3.14
License-File: LICENSE
Requires-Dist: doroutes>=0.2.0
Requires-Dist: gdsfactory>=9.15.0,<9.21.7
Requires-Dist: gplugins[meshwell]>=2.0.0 ; extra == "models"
Requires-Dist: jaxellip ; extra == "models"
Requires-Dist: optuna ; extra == "models"
Requires-Dist: ray[tune] ; extra == "models"
Requires-Dist: sax ; extra == "models"
Requires-Dist: scikit-rf ; extra == "models"
Requires-Dist: scqubits ; extra == "models"
Requires-Dist: sympy ; extra == "models"
Requires-Dist: polars ; extra == "models"
Provides-Extra: models
